inject_emoji/__init__.py
inject_emoji/cli.py
inject_emoji/core.py
inject_emoji/inject_emoji.py
inject_emoji-1.0.0.dist-info/DESCRIPTION.rst
inject_emoji-1.0.0.dist-info/METADATA
inject_emoji-1.0.0.dist-info/RECORD
inject_emoji-1.0.0.dist-info/WHEEL
inject_emoji-1.0.0.dist-info/entry_points.txt
inject_emoji-1.0.0.dist-info/metadata.json
inject_emoji-1.0.0.dist-info/top_level.txt
