Metadata-Version: 2.0
Name: inject-emoji
Version: 1.0.0
Summary: Emoji notation expansion.
Home-page: https://github.com/claylo/inject-emoji
Author: Clay Loveless
Author-email: clay@loveless.net
License: The MIT License (MIT)
Provides-Extra: develop
Requires-Dist: coverage; extra == 'develop'
Requires-Dist: coveralls[yaml]; extra == 'develop'
Requires-Dist: pytest; extra == 'develop'
Requires-Dist: pytest-instafail; extra == 'develop'
Provides-Extra: test
Requires-Dist: coverage; extra == 'test'
Requires-Dist: coveralls; extra == 'test'
Requires-Dist: pytest; extra == 'test'
Requires-Dist: pytest-instafail; extra == 'test'
